[
    {
        "courseid": "12",
        "advworkid": "14",
        "userid": "17",
        "capabilityid": "1",
        "domainvalueid": "1",
        "probability": "0.78775",
        "capabilityoverallgrade": "B",
        "capabilityoverallvalue": "0.94281",
        "iscumulated": "0"
    },
    {
        "courseid": "12",
        "advworkid": "14",
        "userid": "17",
        "capabilityid": "1",
        "domainvalueid": "2",
        "probability": "0.11249",
        "capabilityoverallgrade": "B",
        "capabilityoverallvalue": "0.94281",
        "iscumulated": "0"
    },
    {
        "courseid": "12",
        "advworkid": "14",
        "userid": "17",
        "capabilityid": "1",
        "domainvalueid": "3",
        "probability": "0.05785",
        "capabilityoverallgrade": "B",
        "capabilityoverallvalue": "0.94281",
        "iscumulated": "0"
    },
    {
        "courseid": "12",
        "advworkid": "14",
        "userid": "17",
        "capabilityid": "1",
        "domainvalueid": "4",
        "probability": "0.02787",
        "capabilityoverallgrade": "B",
        "capabilityoverallvalue": "0.94281",
        "iscumulated": "0"
    },
    {
        "courseid": "12",
        "advworkid": "14",
        "userid": "17",
        "capabilityid": "1",
        "domainvalueid": "5",
        "probability": "0.01188",
        "capabilityoverallgrade": "B",
        "capabilityoverallvalue": "0.94281",
        "iscumulated": "0"
    },
    {
        "courseid": "12",
        "advworkid": "14",
        "userid": "17",
        "capabilityid": "1",
        "domainvalueid": "6",
        "probability": "0.00216",
        "capabilityoverallgrade": "B",
        "capabilityoverallvalue": "0.94281",
        "iscumulated": "0"
    },
    {
        "courseid": "12",
        "advworkid": "14",
        "userid": "17",
        "capabilityid": "2",
        "domainvalueid": "1",
        "probability": "0.78460",
        "capabilityoverallgrade": "B",
        "capabilityoverallvalue": "0.94969",
        "iscumulated": "0"
    },
    {
        "courseid": "12",
        "advworkid": "14",
        "userid": "17",
        "capabilityid": "2",
        "domainvalueid": "2",
        "probability": "0.16801",
        "capabilityoverallgrade": "B",
        "capabilityoverallvalue": "0.94969",
        "iscumulated": "0"
    },
    {
        "courseid": "12",
        "advworkid": "14",
        "userid": "17",
        "capabilityid": "2",
        "domainvalueid": "3",
        "probability": "0.02476",
        "capabilityoverallgrade": "B",
        "capabilityoverallvalue": "0.94969",
        "iscumulated": "0"
    },
    {
        "courseid": "12",
        "advworkid": "14",
        "userid": "17",
        "capabilityid": "2",
        "domainvalueid": "4",
        "probability": "0.01214",
        "capabilityoverallgrade": "B",
        "capabilityoverallvalue": "0.94969",
        "iscumulated": "0"
    },
    {
        "courseid": "12",
        "advworkid": "14",
        "userid": "17",
        "capabilityid": "2",
        "domainvalueid": "5",
        "probability": "0.00706",
        "capabilityoverallgrade": "B",
        "capabilityoverallvalue": "0.94969",
        "iscumulated": "0"
    },
    {
        "courseid": "12",
        "advworkid": "14",
        "userid": "17",
        "capabilityid": "2",
        "domainvalueid": "6",
        "probability": "0.00341",
        "capabilityoverallgrade": "B",
        "capabilityoverallvalue": "0.94969",
        "iscumulated": "0"
    },
    {
        "courseid": "12",
        "advworkid": "14",
        "userid": "17",
        "capabilityid": "3",
        "domainvalueid": "1",
        "probability": "1.00000",
        "capabilityoverallgrade": "A",
        "capabilityoverallvalue": "1.00000",
        "iscumulated": "0"
    },
    {
        "courseid": "12",
        "advworkid": "14",
        "userid": "17",
        "capabilityid": "3",
        "domainvalueid": "2",
        "probability": "0.00000",
        "capabilityoverallgrade": "A",
        "capabilityoverallvalue": "1.00000",
        "iscumulated": "0"
    },
    {
        "courseid": "12",
        "advworkid": "14",
        "userid": "17",
        "capabilityid": "3",
        "domainvalueid": "3",
        "probability": "0.00000",
        "capabilityoverallgrade": "A",
        "capabilityoverallvalue": "1.00000",
        "iscumulated": "0"
    },
    {
        "courseid": "12",
        "advworkid": "14",
        "userid": "17",
        "capabilityid": "3",
        "domainvalueid": "4",
        "probability": "0.00000",
        "capabilityoverallgrade": "A",
        "capabilityoverallvalue": "1.00000",
        "iscumulated": "0"
    },
    {
        "courseid": "12",
        "advworkid": "14",
        "userid": "17",
        "capabilityid": "3",
        "domainvalueid": "5",
        "probability": "0.00000",
        "capabilityoverallgrade": "A",
        "capabilityoverallvalue": "1.00000",
        "iscumulated": "0"
    },
    {
        "courseid": "12",
        "advworkid": "14",
        "userid": "17",
        "capabilityid": "3",
        "domainvalueid": "6",
        "probability": "0.00000",
        "capabilityoverallgrade": "A",
        "capabilityoverallvalue": "1.00000",
        "iscumulated": "0"
    },
    {
        "courseid": "12",
        "advworkid": "14",
        "userid": "18",
        "capabilityid": "1",
        "domainvalueid": "1",
        "probability": "0.00112",
        "capabilityoverallgrade": "F",
        "capabilityoverallvalue": "0.30889",
        "iscumulated": "0"
    },
    {
        "courseid": "12",
        "advworkid": "14",
        "userid": "18",
        "capabilityid": "1",
        "domainvalueid": "2",
        "probability": "0.00412",
        "capabilityoverallgrade": "F",
        "capabilityoverallvalue": "0.30889",
        "iscumulated": "0"
    },
    {
        "courseid": "12",
        "advworkid": "14",
        "userid": "18",
        "capabilityid": "1",
        "domainvalueid": "3",
        "probability": "0.00649",
        "capabilityoverallgrade": "F",
        "capabilityoverallvalue": "0.30889",
        "iscumulated": "0"
    },
    {
        "courseid": "12",
        "advworkid": "14",
        "userid": "18",
        "capabilityid": "1",
        "domainvalueid": "4",
        "probability": "0.01857",
        "capabilityoverallgrade": "F",
        "capabilityoverallvalue": "0.30889",
        "iscumulated": "0"
    },
    {
        "courseid": "12",
        "advworkid": "14",
        "userid": "18",
        "capabilityid": "1",
        "domainvalueid": "5",
        "probability": "0.05917",
        "capabilityoverallgrade": "F",
        "capabilityoverallvalue": "0.30889",
        "iscumulated": "0"
    },
    {
        "courseid": "12",
        "advworkid": "14",
        "userid": "18",
        "capabilityid": "1",
        "domainvalueid": "6",
        "probability": "0.91053",
        "capabilityoverallgrade": "F",
        "capabilityoverallvalue": "0.30889",
        "iscumulated": "0"
    },
    {
        "courseid": "12",
        "advworkid": "14",
        "userid": "18",
        "capabilityid": "2",
        "domainvalueid": "1",
        "probability": "0.00000",
        "capabilityoverallgrade": "F",
        "capabilityoverallvalue": "0.35169",
        "iscumulated": "0"
    },
    {
        "courseid": "12",
        "advworkid": "14",
        "userid": "18",
        "capabilityid": "2",
        "domainvalueid": "2",
        "probability": "0.00000",
        "capabilityoverallgrade": "F",
        "capabilityoverallvalue": "0.35169",
        "iscumulated": "0"
    },
    {
        "courseid": "12",
        "advworkid": "14",
        "userid": "18",
        "capabilityid": "2",
        "domainvalueid": "3",
        "probability": "0.00017",
        "capabilityoverallgrade": "F",
        "capabilityoverallvalue": "0.35169",
        "iscumulated": "0"
    },
    {
        "courseid": "12",
        "advworkid": "14",
        "userid": "18",
        "capabilityid": "2",
        "domainvalueid": "4",
        "probability": "0.02139",
        "capabilityoverallgrade": "F",
        "capabilityoverallvalue": "0.35169",
        "iscumulated": "0"
    },
    {
        "courseid": "12",
        "advworkid": "14",
        "userid": "18",
        "capabilityid": "2",
        "domainvalueid": "5",
        "probability": "0.20773",
        "capabilityoverallgrade": "F",
        "capabilityoverallvalue": "0.35169",
        "iscumulated": "0"
    },
    {
        "courseid": "12",
        "advworkid": "14",
        "userid": "18",
        "capabilityid": "2",
        "domainvalueid": "6",
        "probability": "0.77071",
        "capabilityoverallgrade": "F",
        "capabilityoverallvalue": "0.35169",
        "iscumulated": "0"
    },
    {
        "courseid": "12",
        "advworkid": "14",
        "userid": "18",
        "capabilityid": "3",
        "domainvalueid": "1",
        "probability": "0.00000",
        "capabilityoverallgrade": "F",
        "capabilityoverallvalue": "0.28376",
        "iscumulated": "0"
    },
    {
        "courseid": "12",
        "advworkid": "14",
        "userid": "18",
        "capabilityid": "3",
        "domainvalueid": "2",
        "probability": "0.00000",
        "capabilityoverallgrade": "F",
        "capabilityoverallvalue": "0.28376",
        "iscumulated": "0"
    },
    {
        "courseid": "12",
        "advworkid": "14",
        "userid": "18",
        "capabilityid": "3",
        "domainvalueid": "3",
        "probability": "0.00003",
        "capabilityoverallgrade": "F",
        "capabilityoverallvalue": "0.28376",
        "iscumulated": "0"
    },
    {
        "courseid": "12",
        "advworkid": "14",
        "userid": "18",
        "capabilityid": "3",
        "domainvalueid": "4",
        "probability": "0.00069",
        "capabilityoverallgrade": "F",
        "capabilityoverallvalue": "0.28376",
        "iscumulated": "0"
    },
    {
        "courseid": "12",
        "advworkid": "14",
        "userid": "18",
        "capabilityid": "3",
        "domainvalueid": "5",
        "probability": "0.02600",
        "capabilityoverallgrade": "F",
        "capabilityoverallvalue": "0.28376",
        "iscumulated": "0"
    },
    {
        "courseid": "12",
        "advworkid": "14",
        "userid": "18",
        "capabilityid": "3",
        "domainvalueid": "6",
        "probability": "0.97329",
        "capabilityoverallgrade": "F",
        "capabilityoverallvalue": "0.28376",
        "iscumulated": "0"
    },
    {
        "courseid": "12",
        "advworkid": "14",
        "userid": "19",
        "capabilityid": "1",
        "domainvalueid": "1",
        "probability": "0.00147",
        "capabilityoverallgrade": "F",
        "capabilityoverallvalue": "0.33773",
        "iscumulated": "0"
    },
    {
        "courseid": "12",
        "advworkid": "14",
        "userid": "19",
        "capabilityid": "1",
        "domainvalueid": "2",
        "probability": "0.00948",
        "capabilityoverallgrade": "F",
        "capabilityoverallvalue": "0.33773",
        "iscumulated": "0"
    },
    {
        "courseid": "12",
        "advworkid": "14",
        "userid": "19",
        "capabilityid": "1",
        "domainvalueid": "3",
        "probability": "0.01711",
        "capabilityoverallgrade": "F",
        "capabilityoverallvalue": "0.33773",
        "iscumulated": "0"
    },
    {
        "courseid": "12",
        "advworkid": "14",
        "userid": "19",
        "capabilityid": "1",
        "domainvalueid": "4",
        "probability": "0.03725",
        "capabilityoverallgrade": "F",
        "capabilityoverallvalue": "0.33773",
        "iscumulated": "0"
    },
    {
        "courseid": "12",
        "advworkid": "14",
        "userid": "19",
        "capabilityid": "1",
        "domainvalueid": "5",
        "probability": "0.09528",
        "capabilityoverallgrade": "F",
        "capabilityoverallvalue": "0.33773",
        "iscumulated": "0"
    },
    {
        "courseid": "12",
        "advworkid": "14",
        "userid": "19",
        "capabilityid": "1",
        "domainvalueid": "6",
        "probability": "0.83941",
        "capabilityoverallgrade": "F",
        "capabilityoverallvalue": "0.33773",
        "iscumulated": "0"
    },
    {
        "courseid": "12",
        "advworkid": "14",
        "userid": "19",
        "capabilityid": "2",
        "domainvalueid": "1",
        "probability": "0.00000",
        "capabilityoverallgrade": "F",
        "capabilityoverallvalue": "0.45851",
        "iscumulated": "0"
    },
    {
        "courseid": "12",
        "advworkid": "14",
        "userid": "19",
        "capabilityid": "2",
        "domainvalueid": "2",
        "probability": "0.00033",
        "capabilityoverallgrade": "F",
        "capabilityoverallvalue": "0.45851",
        "iscumulated": "0"
    },
    {
        "courseid": "12",
        "advworkid": "14",
        "userid": "19",
        "capabilityid": "2",
        "domainvalueid": "3",
        "probability": "0.03350",
        "capabilityoverallgrade": "F",
        "capabilityoverallvalue": "0.45851",
        "iscumulated": "0"
    },
    {
        "courseid": "12",
        "advworkid": "14",
        "userid": "19",
        "capabilityid": "2",
        "domainvalueid": "4",
        "probability": "0.15064",
        "capabilityoverallgrade": "F",
        "capabilityoverallvalue": "0.45851",
        "iscumulated": "0"
    },
    {
        "courseid": "12",
        "advworkid": "14",
        "userid": "19",
        "capabilityid": "2",
        "domainvalueid": "5",
        "probability": "0.31290",
        "capabilityoverallgrade": "F",
        "capabilityoverallvalue": "0.45851",
        "iscumulated": "0"
    },
    {
        "courseid": "12",
        "advworkid": "14",
        "userid": "19",
        "capabilityid": "2",
        "domainvalueid": "6",
        "probability": "0.50264",
        "capabilityoverallgrade": "F",
        "capabilityoverallvalue": "0.45851",
        "iscumulated": "0"
    },
    {
        "courseid": "12",
        "advworkid": "14",
        "userid": "19",
        "capabilityid": "3",
        "domainvalueid": "1",
        "probability": "0.00000",
        "capabilityoverallgrade": "F",
        "capabilityoverallvalue": "0.29013",
        "iscumulated": "0"
    },
    {
        "courseid": "12",
        "advworkid": "14",
        "userid": "19",
        "capabilityid": "3",
        "domainvalueid": "2",
        "probability": "0.00001",
        "capabilityoverallgrade": "F",
        "capabilityoverallvalue": "0.29013",
        "iscumulated": "0"
    },
    {
        "courseid": "12",
        "advworkid": "14",
        "userid": "19",
        "capabilityid": "3",
        "domainvalueid": "3",
        "probability": "0.00012",
        "capabilityoverallgrade": "F",
        "capabilityoverallvalue": "0.29013",
        "iscumulated": "0"
    },
    {
        "courseid": "12",
        "advworkid": "14",
        "userid": "19",
        "capabilityid": "3",
        "domainvalueid": "4",
        "probability": "0.00198",
        "capabilityoverallgrade": "F",
        "capabilityoverallvalue": "0.29013",
        "iscumulated": "0"
    },
    {
        "courseid": "12",
        "advworkid": "14",
        "userid": "19",
        "capabilityid": "3",
        "domainvalueid": "5",
        "probability": "0.04376",
        "capabilityoverallgrade": "F",
        "capabilityoverallvalue": "0.29013",
        "iscumulated": "0"
    },
    {
        "courseid": "12",
        "advworkid": "14",
        "userid": "19",
        "capabilityid": "3",
        "domainvalueid": "6",
        "probability": "0.95413",
        "capabilityoverallgrade": "F",
        "capabilityoverallvalue": "0.29013",
        "iscumulated": "0"
    },
    {
        "courseid": "12",
        "advworkid": "14",
        "userid": "20",
        "capabilityid": "1",
        "domainvalueid": "1",
        "probability": "0.00288",
        "capabilityoverallgrade": "F",
        "capabilityoverallvalue": "0.47687",
        "iscumulated": "0"
    },
    {
        "courseid": "12",
        "advworkid": "14",
        "userid": "20",
        "capabilityid": "1",
        "domainvalueid": "2",
        "probability": "0.00970",
        "capabilityoverallgrade": "F",
        "capabilityoverallvalue": "0.47687",
        "iscumulated": "0"
    },
    {
        "courseid": "12",
        "advworkid": "14",
        "userid": "20",
        "capabilityid": "1",
        "domainvalueid": "3",
        "probability": "0.01807",
        "capabilityoverallgrade": "F",
        "capabilityoverallvalue": "0.47687",
        "iscumulated": "0"
    },
    {
        "courseid": "12",
        "advworkid": "14",
        "userid": "20",
        "capabilityid": "1",
        "domainvalueid": "4",
        "probability": "0.04601",
        "capabilityoverallgrade": "F",
        "capabilityoverallvalue": "0.47687",
        "iscumulated": "0"
    },
    {
        "courseid": "12",
        "advworkid": "14",
        "userid": "20",
        "capabilityid": "1",
        "domainvalueid": "5",
        "probability": "0.50692",
        "capabilityoverallgrade": "F",
        "capabilityoverallvalue": "0.47687",
        "iscumulated": "0"
    },
    {
        "courseid": "12",
        "advworkid": "14",
        "userid": "20",
        "capabilityid": "1",
        "domainvalueid": "6",
        "probability": "0.41642",
        "capabilityoverallgrade": "F",
        "capabilityoverallvalue": "0.47687",
        "iscumulated": "0"
    },
    {
        "courseid": "12",
        "advworkid": "14",
        "userid": "20",
        "capabilityid": "2",
        "domainvalueid": "1",
        "probability": "0.00000",
        "capabilityoverallgrade": "F",
        "capabilityoverallvalue": "0.44703",
        "iscumulated": "0"
    },
    {
        "courseid": "12",
        "advworkid": "14",
        "userid": "20",
        "capabilityid": "2",
        "domainvalueid": "2",
        "probability": "0.00000",
        "capabilityoverallgrade": "F",
        "capabilityoverallvalue": "0.44703",
        "iscumulated": "0"
    },
    {
        "courseid": "12",
        "advworkid": "14",
        "userid": "20",
        "capabilityid": "2",
        "domainvalueid": "3",
        "probability": "0.00660",
        "capabilityoverallgrade": "F",
        "capabilityoverallvalue": "0.44703",
        "iscumulated": "0"
    },
    {
        "courseid": "12",
        "advworkid": "14",
        "userid": "20",
        "capabilityid": "2",
        "domainvalueid": "4",
        "probability": "0.14362",
        "capabilityoverallgrade": "F",
        "capabilityoverallvalue": "0.44703",
        "iscumulated": "0"
    },
    {
        "courseid": "12",
        "advworkid": "14",
        "userid": "20",
        "capabilityid": "2",
        "domainvalueid": "5",
        "probability": "0.33085",
        "capabilityoverallgrade": "F",
        "capabilityoverallvalue": "0.44703",
        "iscumulated": "0"
    },
    {
        "courseid": "12",
        "advworkid": "14",
        "userid": "20",
        "capabilityid": "2",
        "domainvalueid": "6",
        "probability": "0.51893",
        "capabilityoverallgrade": "F",
        "capabilityoverallvalue": "0.44703",
        "iscumulated": "0"
    },
    {
        "courseid": "12",
        "advworkid": "14",
        "userid": "20",
        "capabilityid": "3",
        "domainvalueid": "1",
        "probability": "0.00000",
        "capabilityoverallgrade": "E",
        "capabilityoverallvalue": "0.60000",
        "iscumulated": "0"
    },
    {
        "courseid": "12",
        "advworkid": "14",
        "userid": "20",
        "capabilityid": "3",
        "domainvalueid": "2",
        "probability": "0.00000",
        "capabilityoverallgrade": "E",
        "capabilityoverallvalue": "0.60000",
        "iscumulated": "0"
    },
    {
        "courseid": "12",
        "advworkid": "14",
        "userid": "20",
        "capabilityid": "3",
        "domainvalueid": "3",
        "probability": "0.00000",
        "capabilityoverallgrade": "E",
        "capabilityoverallvalue": "0.60000",
        "iscumulated": "0"
    },
    {
        "courseid": "12",
        "advworkid": "14",
        "userid": "20",
        "capabilityid": "3",
        "domainvalueid": "4",
        "probability": "0.00000",
        "capabilityoverallgrade": "E",
        "capabilityoverallvalue": "0.60000",
        "iscumulated": "0"
    },
    {
        "courseid": "12",
        "advworkid": "14",
        "userid": "20",
        "capabilityid": "3",
        "domainvalueid": "5",
        "probability": "1.00000",
        "capabilityoverallgrade": "E",
        "capabilityoverallvalue": "0.60000",
        "iscumulated": "0"
    },
    {
        "courseid": "12",
        "advworkid": "14",
        "userid": "20",
        "capabilityid": "3",
        "domainvalueid": "6",
        "probability": "0.00000",
        "capabilityoverallgrade": "E",
        "capabilityoverallvalue": "0.60000",
        "iscumulated": "0"
    }
]